django_ignite-0.1.0.dist-info/licenses/LICENSE
ignite/__init__.py
ignite/cli.py
ignite/env_manager.py
ignite/project_creator.py
ignite/utils.py
django_ignite-0.1.0.dist-info/METADATA
django_ignite-0.1.0.dist-info/WHEEL
django_ignite-0.1.0.dist-info/entry_points.txt
django_ignite-0.1.0.dist-info/top_level.txt
django_ignite-0.1.0.dist-info/RECORD
