Metadata-Version: 2.4
Name: django-ignite
Version: 0.1.0
Summary: CLI tool to scaffold Django projects with modern practices
Author-email: Nazmul Hassan <nazmul.naaz96@gmail.com>
License: MIT
Project-URL: Homepage, https://github.com/HassanNazmul/django-ignite
Project-URL: Repository, https://github.com/HassanNazmul/django-ignite
Project-URL: Issues, https://github.com/HassanNazmul/django-ignite
Requires-Python: >=3.8
License-File: LICENSE
Requires-Dist: click>=8.0
Requires-Dist: InquirerPy>=0.3
Requires-Dist: rich>=13.0
Dynamic: license-file
